README
setup.cfg
setup.py
metaserializer/__init__.py
metaserializer/msjson.py
metaserializer/msphp.py
metaserializer/mspickle.py
metaserializer/msplist.py
metaserializer/msyaml.py
metaserializer/tests.py
metaserializer.egg-info/PKG-INFO
metaserializer.egg-info/SOURCES.txt
metaserializer.egg-info/dependency_links.txt
metaserializer.egg-info/requires.txt
metaserializer.egg-info/top_level.txt