Metadata-Version: 1.1
Name: metaserializer
Version: 0.005
Summary: A cover library for various other serializers.
Home-page: http://packages.python.org/metaserializer
Author: K. Richard Pixley
Author-email: rich@noir.com
License: MIT
Keywords: serializer yaml pickle
Platform: UNKNOWN
Classifier: Development Status :: 2 - Pre-Alpha
Classifier: Intended Audience :: Developers
Classifier: License :: OSI Approved :: MIT License
Classifier: Natural Language :: English
Classifier: Operating System :: OS Independent
Classifier: Programming Language :: Python
Classifier: Programming Language :: Python :: 2.6
Classifier: Topic :: Software Development :: Libraries :: Python Modules
Requires: json
Requires: phpserialize
Requires: pickle
Requires: plistlib
Requires: yaml
Provides: metaserializer
